CHANGES.txt
LICENSE.txt
README.md
setup.py
RsaLibrary/__init__.py
RsaLibrary/_keywords.py
RsaLibrary/version.py
RsaLibrary/test/__init__.py
RsaLibrary/test/test_RsaLibraryKeywords.py
robotframework_RsaLibrary.egg-info/PKG-INFO
robotframework_RsaLibrary.egg-info/SOURCES.txt
robotframework_RsaLibrary.egg-info/dependency_links.txt
robotframework_RsaLibrary.egg-info/requires.txt
robotframework_RsaLibrary.egg-info/top_level.txt