Metadata-Version: 1.0
Name: robotframework-RsaLibrary
Version: 0.0.5-dev
Summary: Robot Framework Library allowing to encrypt and decrypt data
Home-page: https://code.google.com/p/robotframework-RsaLibrary/
Author: Jules Barnes
Author-email: jules@julesbarnes.com
License: LICENSE.txt
Platform: UNKNOWN
